font_caladea/__init__.py
font_caladea/files/APACHE-2.0.txt
font_caladea/files/Caladea-Bold.ttf
font_caladea/files/Caladea-BoldItalic.ttf
font_caladea/files/Caladea-Italic.ttf
font_caladea/files/Caladea-Regular.ttf
font_caladea-0.0.2.dist-info/DESCRIPTION.rst
font_caladea-0.0.2.dist-info/METADATA
font_caladea-0.0.2.dist-info/RECORD
font_caladea-0.0.2.dist-info/WHEEL
font_caladea-0.0.2.dist-info/entry_points.txt
font_caladea-0.0.2.dist-info/metadata.json
font_caladea-0.0.2.dist-info/top_level.txt
